{
  "wls_baseline": {
    "theta_deg": 7.7133693419621885,
    "|V|": 0.09075134247541428
  },
  "results": [
    {
      "tag": "W96",
      "use_bus_smooth": true,
      "epochs": 60,
      "lr": 0.001,
      "hidden": 256,
      "layers": 2,
      "nhead": 4,
      "bias_scale": 0.0,
      "use_mask": false,
      "trust_lambda": 0.0,
      "val_loss": 0.012350897304713726,
      "test_theta_deg": 5.6529228236305435,
      "test_|V|": 0.019577665254473686,
      "S": 66,
      "M": 72,
      "Nbus": 33,
      "w_temp_th": 0.0001,
      "w_temp_vm": 0.0001,
      "wls_theta_deg": 7.7133693419621885,
      "wls_|V|": 0.09075134247541428
    },
    {
      "tag": "W96",
      "use_bus_smooth": true,
      "epochs": 60,
      "lr": 0.001,
      "hidden": 256,
      "layers": 2,
      "nhead": 4,
      "bias_scale": 0.0,
      "use_mask": false,
      "trust_lambda": 0.001,
      "val_loss": 0.01161813735961914,
      "test_theta_deg": 5.455767492247421,
      "test_|V|": 0.02006350364536047,
      "S": 66,
      "M": 72,
      "Nbus": 33,
      "w_temp_th": 0.0001,
      "w_temp_vm": 0.0001,
      "wls_theta_deg": 7.7133693419621885,
      "wls_|V|": 0.09075134247541428
    },
    {
      "tag": "W96",
      "use_bus_smooth": true,
      "epochs": 60,
      "lr": 0.001,
      "hidden": 256,
      "layers": 2,
      "nhead": 4,
      "bias_scale": 3.0,
      "use_mask": false,
      "trust_lambda": 0.0,
      "val_loss": 0.010853366926312447,
      "test_theta_deg": 5.312538638795666,
      "test_|V|": 0.01881442777812481,
      "S": 66,
      "M": 72,
      "Nbus": 33,
      "w_temp_th": 0.0001,
      "w_temp_vm": 0.0001,
      "wls_theta_deg": 7.7133693419621885,
      "wls_|V|": 0.09075134247541428
    },
    {
      "tag": "W96",
      "use_bus_smooth": true,
      "epochs": 60,
      "lr": 0.001,
      "hidden": 256,
      "layers": 2,
      "nhead": 4,
      "bias_scale": 3.0,
      "use_mask": false,
      "trust_lambda": 0.001,
      "val_loss": 0.012434190139174461,
      "test_theta_deg": 5.603995830728215,
      "test_|V|": 0.018451504409313202,
      "S": 66,
      "M": 72,
      "Nbus": 33,
      "w_temp_th": 0.0001,
      "w_temp_vm": 0.0001,
      "wls_theta_deg": 7.7133693419621885,
      "wls_|V|": 0.09075134247541428
    },
    {
      "tag": "W96",
      "use_bus_smooth": true,
      "epochs": 60,
      "lr": 0.0003,
      "hidden": 256,
      "layers": 2,
      "nhead": 4,
      "bias_scale": 0.0,
      "use_mask": false,
      "trust_lambda": 0.0,
      "val_loss": 0.019702132791280746,
      "test_theta_deg": 6.961666256110677,
      "test_|V|": 0.023732340894639492,
      "S": 66,
      "M": 72,
      "Nbus": 33,
      "w_temp_th": 0.0001,
      "w_temp_vm": 0.0001,
      "wls_theta_deg": 7.7133693419621885,
      "wls_|V|": 0.09075134247541428
    },
    {
      "tag": "W96",
      "use_bus_smooth": true,
      "epochs": 60,
      "lr": 0.0003,
      "hidden": 256,
      "layers": 2,
      "nhead": 4,
      "bias_scale": 0.0,
      "use_mask": false,
      "trust_lambda": 0.001,
      "val_loss": 0.017566556110978127,
      "test_theta_deg": 7.141313678216941,
      "test_|V|": 0.019459446892142296,
      "S": 66,
      "M": 72,
      "Nbus": 33,
      "w_temp_th": 0.0001,
      "w_temp_vm": 0.0001,
      "wls_theta_deg": 7.7133693419621885,
      "wls_|V|": 0.09075134247541428
    },
    {
      "tag": "W96",
      "use_bus_smooth": true,
      "epochs": 60,
      "lr": 0.0003,
      "hidden": 256,
      "layers": 2,
      "nhead": 4,
      "bias_scale": 3.0,
      "use_mask": false,
      "trust_lambda": 0.0,
      "val_loss": 0.01599285751581192,
      "test_theta_deg": 6.953291376971183,
      "test_|V|": 0.01987295877188444,
      "S": 66,
      "M": 72,
      "Nbus": 33,
      "w_temp_th": 0.0001,
      "w_temp_vm": 0.0001,
      "wls_theta_deg": 7.7133693419621885,
      "wls_|V|": 0.09075134247541428
    },
    {
      "tag": "W96",
      "use_bus_smooth": true,
      "epochs": 60,
      "lr": 0.0003,
      "hidden": 256,
      "layers": 2,
      "nhead": 4,
      "bias_scale": 3.0,
      "use_mask": false,
      "trust_lambda": 0.001,
      "val_loss": 0.017905376851558685,
      "test_theta_deg": 6.880405788007742,
      "test_|V|": 0.020375636406242847,
      "S": 66,
      "M": 72,
      "Nbus": 33,
      "w_temp_th": 0.0001,
      "w_temp_vm": 0.0001,
      "wls_theta_deg": 7.7133693419621885,
      "wls_|V|": 0.09075134247541428
    }
  ]
}